LICENSE
MANIFEST.in
README.md
setup.py
licen/__init__.py
licen/main.py
licen.egg-info/PKG-INFO
licen.egg-info/SOURCES.txt
licen.egg-info/dependency_links.txt
licen.egg-info/entry_points.txt
licen.egg-info/requires.txt
licen.egg-info/top_level.txt
licen/templates/headers/agpl-3.0-header
licen/templates/headers/apache-2.0-header
licen/templates/headers/gpl-2.0-header
licen/templates/headers/gpl-3.0-header
licen/templates/headers/lgpl-2.1-header
licen/templates/licenses/agpl-3.0
licen/templates/licenses/apache-2.0
licen/templates/licenses/artistic-2.0
licen/templates/licenses/bsd-2-clause
licen/templates/licenses/bsd-3-clause
licen/templates/licenses/cc0
licen/templates/licenses/epl-1.0
licen/templates/licenses/gpl-2.0
licen/templates/licenses/gpl-3.0
licen/templates/licenses/isc
licen/templates/licenses/lgpl-2.1
licen/templates/licenses/lgpl-3.0
licen/templates/licenses/mit
licen/templates/licenses/mpl-2.0
licen/templates/licenses/no-license
licen/templates/licenses/unlicense