Metadata-Version: 1.1
Name: licen
Version: 0.1.0
Summary: generate the license for you
Home-page: http://github.com/lord63/licen
Author: lord63
Author-email: lord63.j@gmail.com
License: MIT
Keywords: license generate cli
Platform: UNKNOWN
Classifier: Development Status :: 4 - Beta
Classifier: Intended Audience :: Developers
Classifier: Operating System :: POSIX
Classifier: Operating System :: POSIX :: Linux
Classifier: License :: OSI Approved :: MIT License
Classifier: Programming Language :: Python :: 2
Classifier: Programming Language :: Python :: 2.7
